radhesh/__init__.py
radhesh/ao_star.py
radhesh/astar.py
radhesh/bfs.py
radhesh/climbing.py
radhesh/dfs.py
radhesh/dfs_id.py
radhesh/dfs_limited.py
radhesh/steepest_ascent.py
radhesh/test.py
radhesh/tsp.py
radhesh/ucs.py
radhesh/water_jug.py
radhesh-0.1.2.dist-info/METADATA
radhesh-0.1.2.dist-info/WHEEL
radhesh-0.1.2.dist-info/top_level.txt
radhesh-0.1.2.dist-info/RECORD
