Metadata-Version: 2.1
Name: radhesh
Version: 0.1.2
Summary: Algo Land
Author: Radhesh Goel
Author-email: radhesh036916@gmail.com
Classifier: Programming Language :: Python :: 3
Classifier: License :: OSI Approved :: MIT License
Classifier: Operating System :: OS Independent
Requires-Python: >=3.6
